local_control/__init__.py
local_control/app.py
local_control/auth.py
local_control/cli.py
local_control/clipboard.py
local_control/config.py
local_control/control.py
local_control/startup.py
local_control/static/index.html
local_control/static/css/styles.css
local_control/static/js/app.js
local_control/utils/__init__.py
local_control/utils/qrcodegen.py
local_control/utils/terminal_qr.py
local_control-0.1.3.dist-info/licenses/LICENSE
local_control-0.1.3.dist-info/METADATA
local_control-0.1.3.dist-info/WHEEL
local_control-0.1.3.dist-info/entry_points.txt
local_control-0.1.3.dist-info/top_level.txt
local_control-0.1.3.dist-info/RECORD
