Metadata-Version: 2.4
Name: local_control
Version: 0.1.3
Summary: LAN-accessible remote control server for mouse, keyboard, and power management
Author: DIYer22
License: MIT License
Project-URL: Homepage, https://github.com/DIYer22/local_control
Requires-Python: >=3.7
License-File: LICENSE
Requires-Dist: flask>=2.2
Dynamic: license-file
